{
  "success": true,
  "errorCode": 200,
  "errorMsg": null,
  "data": [
    {
      "query": "SELECT * FROM PROD LIMIT 100",
      "success": true,
      "tsv_data": "点击率\t产品ID\t商品信息\t日期\t点击量\t订单量\t曝光量\tTM咨询量\tL1+点击量\t全站商机转化率\tL1+买家点击占比\t全站商机量\tL1+全站商机量\t询盘量\n3.32\t1601739239514\tPremium Handmade Silk Flowers Bouquet for Elegant Wedding Centerpieces Event Floral Arrangement\t2026-05-19~2026-06-17\t186\t0\t5599\t2\t67\t1.08\t36.02\t2\t2\t2\n3.71\t1600679334897\tWholesale Luxury 6oz 8oz 9oz 10oz 12oz Clear Candle Jars Vessels Glass Candle Containers With Lid for Scented Candles\t2026-05-19~2026-06-17\t136\t0\t3663\t5\t38\t5.88\t27.94\t8\t6\t6\n3.02\t1600699042898\tWholesale High Borosilicate Glass Food Storage Container With Lid Sealed Meal Prep Containers Glass Lunch Boxes for Home Kitchen\t2026-05-19~2026-06-17\t97\t0\t3211\t4\t50\t4.12\t51.55\t4\t4\t1\n4.86\t1600619054488\tFood Container Wide Mouth16Oz 500ml Airtight Sealed Glass Mason Jars Jar With Metal Lid for Canning Food\t2026-05-19~2026-06-17\t86\t0\t1771\t3\t35\t4.65\t40.7\t4\t3\t2\n3.41\t1601261083569\tCustom Luxury Clear Glass Candle Jar with Natural Cork Lid and Cylinder Gift Box Packaging for Home Decor Wedding Aromatherapy\t2026-05-19~2026-06-17\t77\t0\t2255\t4\t32\t6.49\t41.56\t5\t3\t4\n3.59\t1601415933060\tAesthetic Electric Candle Warmer Lamp Modern Wood Base Wax Melt Burner Safe Flameless Candle Heater for Home Decor\t2026-05-19~2026-06-17\t54\t0\t1504\t0\t37\t0.0\t68.52\t0\t0\t0\n3.76\t1600486574351\tPrivate Label Custom Wholesale Fancy Luxury Thick Hand Blown Glass Candle Containers Glass Candles Jar Leopard\t2026-05-19~2026-06-17\t46\t0\t1224\t3\t20\t8.7\t43.48\t4\t3\t1\n2.64\t1600146147678\t8oz Wholesale Unique Round Bottom Shape Matte Milky Luxury Glass Candle Jars with Cork Lids\t2026-05-19~2026-06-17\t45\t0\t1706\t1\t13\t4.44\t28.89\t2\t1\t1\n3.02\t1600793932701\tWholesale Tall Home Cylinder Modern Nordic Wedding Decorations Clear Flower Glass Vase\t2026-05-19~2026-06-17\t43\t0\t1422\t1\t23\t4.65\t53.49\t2\t1\t1\n3.51\t1600453691553\tWholesale Glossy Black White Glass Candle Jar 12oz  Empty Glass Candle Jar for Candle Making\t2026-05-19~2026-06-17\t40\t0\t1139\t3\t22\t7.5\t55.0\t3\t3\t2\n2.91\t1601559292172\tBest Selling Glass Candle Jars With Bamboo Lids for Making Candles 17oz Empty Candle Jar for Wedding Decorations 500ml\t2026-05-19~2026-06-17\t40\t0\t1376\t1\t14\t2.5\t35.0\t1\t1\t0\n2.08\t1601381085361\tMatte Frosted Amber Glass Perfume Bottles 50-120ml Wholesale Vintage Round Spray Bottles for Essential Oils and Fragrance\t2026-05-19~2026-06-17\t38\t0\t1828\t5\t28\t13.16\t73.68\t5\t3\t0\n2.12\t1600565199345\tWholesale Custom LOGO 8oz 250g Hotel Long Lasting Rose Scented Soy Candles Luxury Gift Set in Glass Jar\t2026-05-19~2026-06-17\t36\t0\t1696\t1\t24\t2.78\t66.67\t1\t1\t0\n2.6\t1600569954739\tWholesale Modern Hot Sale Luxury White Scented Soy Candles with Custom Labels Scented Candles with Wooden Lid and Gift Box\t2026-05-19~2026-06-17\t33\t0\t1268\t1\t11\t3.03\t33.33\t1\t1\t0\n4.88\t62130425391\tWholesale Soy Candle Jar Luxury with Lid for Candle Making\t2026-05-19~2026-06-17\t32\t0\t656\t0\t12\t0.0\t37.5\t0\t0\t0\n3.76\t1600830185143\tWholesale Frosted White Glass Candle Vessel Matte Black 8oz 10oz Candle Jars With Bamboo Metal Wood Lids in Bulk\t2026-05-19~2026-06-17\t32\t0\t850\t4\t13\t15.63\t40.63\t5\t4\t3\n5.43\t1600619085214\tEmpty Wide Mouth Round Glass Jar 8oz Mason Jar With Airtight Lid for Food Jam Honey Pickle\t2026-05-19~2026-06-17\t31\t0\t571\t5\t6\t25.81\t19.35\t8\t2\t6\n2.75\t1601560051799\tStock Available Glass Candle Jars Glass Candle Holders Lanterns Candle Jars\t2026-05-19~2026-06-17\t30\t0\t1089\t1\t7\t3.33\t23.33\t1\t1\t0\n3.08\t1600651429327\tCrystal Glass Candle Holder Decorate Glass Decorations Nordic Candle Stick Holder Decorative Candle Stand\t2026-05-19~2026-06-17\t29\t0\t941\t1\t19\t3.45\t65.52\t1\t1\t0\n2.48\t1601164997955\tWholesale Multi-Colored Glass Candle Jars Luxury Geo Cut Candy Jar Glass Storage Jar With Glass Lid\t2026-05-19~2026-06-17\t28\t0\t1127\t2\t11\t7.14\t39.29\t2\t1\t0\n5.36\t1600865035707\tLeopard Print Handmade Black White Amber Empty Glass Candle Jar Wholesale Candle Jars  for Candle Making\t2026-05-19~2026-06-17\t27\t0\t504\t1\t11\t7.41\t40.74\t2\t1\t2\n2.98\t1600838029358\tCustom 8oz Unique Round Bottom Shape Clear Frosted Matte Luxury Glass Candle Jars with Cork Lid or Metal Lid\t2026-05-19~2026-06-17\t26\t0\t872\t0\t7\t0.0\t26.92\t0\t0\t0\n3.87\t1601213636318\t1400ml Double Layer Large Capacity Plastic Lunch Box With Cutlery Office School Portable Breakfast Picnic Container\t2026-05-19~2026-06-17\t26\t0\t671\t1\t9\t3.85\t34.62\t1\t1\t0\n3.3\t1601670043882\tPopular Custom Round High Borosilicate Glass Jar Long Lasting Aromatherapy Natural Soy Scented Candle with Wood Ball Cork Lid\t2026-05-19~2026-06-17\t26\t0\t787\t0\t13\t3.85\t50.0\t1\t0\t1\n2.9\t60839710755\tWholesale 12 oz clear Glass Candle Jar with Dark Wood Lid for Candle Making\t2026-05-19~2026-06-17\t25\t0\t863\t1\t6\t8.0\t24.0\t2\t1\t1\n2.6\t1601706331362\tGypsum Aromatherapy Wax Tablet Home Wardrobe Deodorizing Aroma Solid Perfume with Gift Car Fragrance\t2026-05-19~2026-06-17\t24\t0\t924\t1\t12\t4.17\t50.0\t1\t1\t0\n2.56\t1600488479015\tWholesale Custom 2026 Luxury 3 Wick Glossy Amber Eco Friendly Glass Candle Jars Large 18OZ Clear Glass Jars for Candle Making\t2026-05-19~2026-06-17\t23\t0\t898\t2\t10\t8.7\t43.48\t2\t1\t0\n2.11\t1601033172878\tCustom Round Bottom Shape Clear Frosted Matte Luxury Glass Candle Jars with Cork Lid or Metal Lid\t2026-05-19~2026-06-17\t23\t0\t1088\t1\t8\t4.35\t34.78\t1\t1\t0\n2.95\t1601519501503\tModern Single Tier Borosilicate Glass Bento Box Square Shape Storage Jar with Bamboo Lid for Freshness Preservation Lunch Boxes\t2026-05-19~2026-06-17\t22\t0\t745\t2\t10\t9.09\t45.45\t2\t2\t0\n2.35\t1600459715985\tWholesale Iridescent Glass Candle Container 12oz Empty Glass Jars for Candle Making\t2026-05-19~2026-06-17\t21\t0\t892\t1\t7\t4.76\t33.33\t1\t1\t0\n2.51\t1600864193733\tWholesale Luxury Clear Crystal Candle Jar Multiple Colors Wedding and Valentine&#39;s Day Decor Bell Dome Glass Cloche in Bulk\t2026-05-19~2026-06-17\t21\t0\t838\t0\t7\t0.0\t33.33\t0\t0\t0\n2.43\t1601430480657\tGlass Ball Modern Electric Candle Warmer Lamp Luxury Fragrance Scented Candle Table Lamp Night Light Timer Switch Aromatherapy\t2026-05-19~2026-06-17\t21\t0\t863\t0\t10\t0.0\t47.62\t0\t0\t0\n3.02\t1601739324044\tWholesale Factory Price Artificial Flowers Bulk Mixed Silk Flower Branches for Garden Decor\t2026-05-19~2026-06-17\t21\t0\t695\t0\t9\t4.76\t42.86\t1\t0\t1\n2.73\t1601769535756\tLuxury Hurricane Glass Cylinder Candle Holder Sleeve Open Ended Clear Windproof Candle Chimney Hotel Table Wedding Centerpiece\t2026-05-19~2026-06-17\t21\t0\t769\t1\t5\t4.76\t23.81\t1\t1\t0\n3.85\t1601132675942\tHot Sell 10oz Exclusive Custom High Quality Luxury Glass Candle Jars for Candle Making Candle Container With Lids\t2026-05-19~2026-06-17\t19\t0\t493\t3\t12\t15.79\t63.16\t3\t3\t0\n2.63\t1601019349217\t8oz Factory Custom Wholesale Unique Round Bottom Shape Matte Milky Luxury Ceramic Candle Jars with Ceramic Lids\t2026-05-19~2026-06-17\t18\t0\t685\t0\t6\t0.0\t33.33\t0\t0\t0\n2.28\t1601395195607\tCustom Luxury Embossed Color Unique Pattern Glass Candle Jars Empty Candle Vessel With Glass Lid\t2026-05-19~2026-06-17\t18\t0\t789\t0\t9\t0.0\t50.0\t0\t0\t0\n2.3\t1601587460494\tCustom Logo Luxury Long Lasting Aromatherapy Scented Candle for Home With Folding Box\t2026-05-19~2026-06-17\t18\t0\t784\t0\t10\t0.0\t55.56\t0\t0\t0\n4.46\t1600488980085\tPrivate Label Large Recycled Translucent Luxury Empty Green Cylinder Glass Candle Jar Vessel From China\t2026-05-19~2026-06-17\t17\t0\t381\t0\t10\t0.0\t58.82\t0\t0\t0\n5.21\t1600539255631\tCustom Luxury 12oz Iridescent Holographic Coloured Empty Glass Scented Candle Container Jar With Lid for Candle Making\t2026-05-19~2026-06-17\t17\t0\t326\t0\t7\t5.88\t41.18\t1\t0\t1\n4.66\t1600932247503\tIridescent Holographic Round Bottom Glass Candle Jar With Wood Lids Candle Jars Glass With Lid and Box\t2026-05-19~2026-06-17\t17\t0\t365\t0\t5\t11.76\t29.41\t2\t2\t2\n2.68\t1601707728512\tNew Indoor Household Lasting Fragrance Incense Removal Artifact Aromatherapy Wardrobe Gypsum Fragrance Pieces Scented Candles\t2026-05-19~2026-06-17\t16\t0\t596\t0\t8\t0.0\t50.0\t0\t0\t0\n5.42\t1601051574772\tWholesale Unique Cylinder 7oz 8 oz Glossy Amber Brown Round Bottom Glass Candle Jar with Cork Lids\t2026-05-19~2026-06-17\t15\t0\t277\t1\t7\t6.67\t46.67\t1\t1\t0\n2.51\t1601304380045\tWholesale Thick Wall Round Bottom Shape Amber Luxury Glass Candle Jars With Cork Lids for Home Decoration\t2026-05-19~2026-06-17\t15\t0\t598\t0\t10\t0.0\t66.67\t0\t0\t0\n3.38\t1601560067707\tHigh Quality Wholesale Glass Jars for Candles Candle Glass Jar  With Lid\t2026-05-19~2026-06-17\t15\t0\t444\t0\t2\t0.0\t13.33\t0\t0\t0\n1.96\t1601670235671\tWholesale Glass Jar with Cork Lid Soy Wax 8oz Private Label Luxury Candles Jar\t2026-05-19~2026-06-17\t15\t0\t767\t1\t6\t6.67\t40.0\t1\t1\t1\n3.09\t1601699015310\tWholesale Luxury Custom Home Decor Air Fresher Aroma Gypsum Stone Scented Wax Tablet Sachet\t2026-05-19~2026-06-17\t15\t0\t485\t0\t9\t0.0\t60.0\t0\t0\t0\n3.73\t1600146372196\tCustom 8oz 10oz 12oz 14oz Frosted White Luxury Glass Candle Jars Empty Jar for Making Valentine&#39;s Day Candles\t2026-05-19~2026-06-17\t14\t0\t375\t2\t7\t21.43\t50.0\t3\t2\t2\n3.05\t1600923287890\tHot Selling Mexican Style Hand Blown Glass Tumbler Small Colored Candle Holder for Valentine&#39;s Day Drinking Glasses\t2026-05-19~2026-06-17\t14\t0\t459\t0\t7\t0.0\t50.0\t0\t0\t0\n3.45\t1601273746315\tHot Selling Decor Soy Wax Elegant Private Label Glass Candle 250ml Bulk Glossy Black Aromatherapy Jar Candle With Packing Box\t2026-05-19~2026-06-17\t14\t0\t406\t1\t9\t7.14\t64.29\t1\t0\t0\n2.51\t1601670232254\tWholesale Custom Logo Private Label Luxury Unique Candle Vessels Amber 4oz 8oz 10oz 12oz Empty Glass Jars With Cork Lid\t2026-05-19~2026-06-17\t14\t0\t558\t0\t2\t0.0\t14.29\t0\t0\t0\n4.17\t1601671039989\tClear Borosilicate Heat Resistant Glass Jars with Wooden Cork Ball Lids for Soy Wax Candle Making for Easter Decorations\t2026-05-19~2026-06-17\t14\t0\t336\t0\t6\t0.0\t42.86\t0\t0\t0\n2.96\t1600426068574\tCustomized Black Frosted Luxury Glass Candle Jar With Metal Lids 3.5oz 8oz 12oz Empty Matte Candle Glass Jar for Candle Making\t2026-05-19~2026-06-17\t13\t0\t439\t1\t5\t7.69\t38.46\t1\t0\t0\n3.33\t1600967800530\tSquare Shape Glass Jars for Storage Food Storage Jar 5oz Square Glass Spice Jar Shaker Lid Airtight\t2026-05-19~2026-06-17\t12\t0\t360\t1\t5\t8.33\t41.67\t1\t1\t0\n3.25\t1601525431189\tAirtight & Leakproof Premium Borosilicate Glass Food Storage Containers\t2026-05-19~2026-06-17\t12\t0\t369\t0\t8\t0.0\t66.67\t0\t0\t0\n2.7\t1600484147393\tWholesale Custom Unique Coloured  Glass Candle Jar With Lid 12oz Luxury Speckled Glass Jar Candle Holder Gift\t2026-05-19~2026-06-17\t11\t0\t408\t1\t4\t18.18\t36.36\t2\t1\t1\n2.8\t1600611720967\tHot Sale Rectangular Meal Prep Containers Airtight Food Storage Container Microwave Safe Lunch Box Glass Lunchbox\t2026-05-19~2026-06-17\t11\t0\t393\t0\t5\t0.0\t45.45\t0\t0\t0\n4.14\t1600987117892\tHot Sale Premier Quality Luxury Pink Vessels Glass Candle Holder Jar With Lid and Custom Box\t2026-05-19~2026-06-17\t11\t0\t266\t0\t4\t0.0\t36.36\t0\t0\t0\n2.62\t1600362130145\tWholesale Fashion Hot Sale Transparent Candle Jar Bell-shaped Dome Cover Glass Candle Holder Aroma Candle Container\t2026-05-19~2026-06-17\t10\t1\t382\t0\t3\t10.0\t30.0\t1\t0\t0\n4.48\t1600543278551\tHot Sale Empty Copper Electroplating Rose Gold Chrome Glass Candle Jars with Luxury Metallic Finish Mirror Lid\t2026-05-19~2026-06-17\t10\t0\t223\t0\t3\t0.0\t30.0\t0\t0\t0\n4.12\t1600699117534\tHot Sales Microwave Oven Safe Glass Food Container Bento Lunch Box Meal Prep Storage Food Container\t2026-05-19~2026-06-17\t10\t0\t243\t0\t9\t0.0\t90.0\t0\t0\t0\n2.35\t1601377570971\tNew Style Glass Candle Holder In Different Colors 175ml 340ml Reusable Thick Wall Glass Candle Jars For Home Decoration\t2026-05-19~2026-06-17\t10\t0\t426\t0\t3\t0.0\t30.0\t0\t0\t0\n1.49\t1601417281221\tOEM ODM Hot-sale Modern Melting Wax Candle Warmer Lamp with Timer Romantic Glass Candle Holder Warmers\t2026-05-19~2026-06-17\t10\t0\t669\t0\t5\t0.0\t50.0\t0\t0\t0\n4.81\t1601560177255\tCustom Private Label 400g Glass Candle Jars With Lids Candle Jars Glass\t2026-05-19~2026-06-17\t10\t0\t208\t1\t3\t10.0\t30.0\t1\t1\t0\n2.33\t1601670100616\tWholesale Transparent White Black Matte Empty 8 oz 10 oz 14 oz Wide Mouth Glass Wax Candle Jar With Wooden Cork Lid\t2026-05-19~2026-06-17\t10\t0\t430\t0\t4\t0.0\t40.0\t0\t0\t0\n5.49\t1600342825930\tCustomized Wholesale High Quality Amber Leopard Print Aromatherapy Candle Jar Home Decor Glassware\t2026-05-19~2026-06-17\t9\t0\t164\t0\t5\t0.0\t55.56\t0\t0\t0\n4.21\t1600427692239\tHigh End Luxury Candle Jars Vessels With Lid Diamond studded Candle Jar Empty Round Glass Candle Jar for Interior Decoration\t2026-05-19~2026-06-17\t9\t0\t214\t0\t2\t0.0\t22.22\t0\t0\t0\n3.25\t1600643922600\t10oz 12oz 16oz Factory Wholesale Luxury Empty Custom Frosted Matte White Black Glass Candle Jar for Candle Making\t2026-05-19~2026-06-17\t9\t0\t277\t0\t4\t11.11\t44.44\t1\t1\t1\n2.39\t1601107153011\tFashion Home Decoration Empty Glass Candle Holder With Round Ball Cork Lid Making Glass Jar Customized Color\t2026-05-19~2026-06-17\t9\t0\t377\t0\t3\t0.0\t33.33\t0\t0\t0\n4.0\t1601670287240\tNatural Candle Jar Empty Candle Bottle High Borosilicat Glass Containers with Cork Lids\t2026-05-19~2026-06-17\t9\t0\t225\t0\t4\t0.0\t44.44\t0\t0\t0\n5.77\t1601770552507\tReliable Supplier Custom Size Heat Resistant Chimney Glass Hurricane Candle Holder Sleeve with Open Ends for Outdoor Events\t2026-05-19~2026-06-17\t9\t0\t156\t0\t6\t0.0\t66.67\t0\t0\t0\n12.7\t60832806973\tWholesale Copper Candle Jar with Lid for Candle Making\t2026-05-19~2026-06-17\t8\t0\t63\t0\t2\t0.0\t25.0\t0\t0\t0\n2.78\t62130432533\tWholesale Glass Candle Jar Container 8 oz for Candle Making\t2026-05-19~2026-06-17\t8\t0\t288\t0\t4\t0.0\t50.0\t0\t0\t0\n2.69\t1600426461716\tWholesale Elegant Metal Candle Jar Luxury Candle Holder Candle Vessel Different Sizes for Decoration\t2026-05-19~2026-06-17\t8\t0\t297\t0\t6\t12.5\t75.0\t1\t1\t1\n2.35\t1600426808650\tCustomize Three Wick Candle Jar Luxury Ceramic Candle Jars with Lid and Boxes Private Label for Interior Decoration\t2026-05-19~2026-06-17\t8\t0\t340\t0\t2\t0.0\t25.0\t0\t0\t0\n5.26\t1600430099489\tWholesale clear Glass Candle Jar with High Quality Nordic pink Glass Candle Holder Label  with Lid for Interior Decoration\t2026-05-19~2026-06-17\t8\t0\t152\t0\t7\t0.0\t87.5\t0\t0\t0\n2.95\t1600503633638\tLuxury Custom Logo 100ml 200ml 250ml Metal Tall Paint Tin Can for Candle Candle Vessels Metal Tin Can\t2026-05-19~2026-06-17\t8\t0\t271\t1\t8\t12.5\t100.0\t1\t1\t0\n2.84\t1600516941147\tCustom Home Decoration Matte White Empty Ceramic Candle Vessel Jar 160ml 280ml Candle Holder Ceramic\t2026-05-19~2026-06-17\t8\t0\t282\t1\t3\t12.5\t37.5\t1\t0\t0\n1.74\t1601112642953\tHot Sale Colorful 13oz Ceramic Candle Jars Can Be Customized With Embossed Logo Ceramic Candle Holder\t2026-05-19~2026-06-17\t8\t0\t459\t0\t4\t0.0\t50.0\t0\t0\t0\n4.17\t1601126808217\tClassic Spa Treatment Cylinder Glass Candle Massage Jar Scented Candle Holder with Spout for Valentine&#39;s Day\t2026-05-19~2026-06-17\t8\t0\t192\t1\t2\t12.5\t25.0\t1\t1\t0\n3.0\t1601415850943\tElectric Candle Heater Lamp Adjustable Height Dimmable Linen Lampshade Timer for Home Decoration Desk Use No Need for Actual\t2026-05-19~2026-06-17\t8\t0\t267\t0\t2\t0.0\t25.0\t0\t0\t0\n4.82\t1601421098102\tHot Selling New Electric Incense Burner Wood and Metal Night Lamp with Timer/Dimmer Switch Scented Candle Warmer Melting Wax\t2026-05-19~2026-06-17\t8\t0\t166\t1\t1\t12.5\t12.5\t1\t1\t0\n1.34\t1601431645939\tElectric Wood and Metal Home Decor Aroma Incense Burner Candle Warmer Wax Melt with Timer\t2026-05-19~2026-06-17\t8\t0\t597\t0\t6\t0.0\t75.0\t0\t0\t0\n8.05\t1600629959848\tMason Jars Wide Mouth Clear 120ml 4oz Mini Canning Jars With Metal Lids for Honey Jam Jelly Baby Foods\t2026-05-19~2026-06-17\t7\t0\t87\t0\t4\t0.0\t57.14\t0\t0\t0\n3.08\t1600650147218\tCustomized Empty 10oz Unique Matte Concrete Candle Jars With Lid Luxury Embossed Logo Cement Candle Jar Matte\t2026-05-19~2026-06-17\t7\t0\t227\t1\t4\t14.29\t57.14\t1\t1\t0\n4.32\t1600739768762\tCustomized Air Freshener Oval Ceramic Scented Stone Car Hanging Scented Ceramic Plaster Stone Scented Candles\t2026-05-19~2026-06-17\t7\t0\t162\t0\t3\t0.0\t42.86\t0\t0\t0\n4.55\t1600904745035\tLuxury Empty 380ml Matte Black White Pink Round Candles Jar Glass Candle Jars With Lid\t2026-05-19~2026-06-17\t7\t0\t154\t0\t6\t0.0\t85.71\t0\t0\t0\n2.19\t1600924667035\tLuxury Unique Wave Shape Amber Gray Frosted Clear 8oz Glass Candle Holders Glass Candle Jar With Lid\t2026-05-19~2026-06-17\t7\t0\t319\t0\t4\t14.29\t57.14\t1\t0\t1\n8.54\t1601001122900\tLuxury Frosted Wholesale White 8oz 10oz 14oz Custom Logo Colorful Wide Mouth Glass Candle Jar for Candle Making\t2026-05-19~2026-06-17\t7\t0\t82\t1\t3\t28.57\t42.86\t2\t1\t1\n5.38\t1601035103105\tWholesale 8oz Unique Round Bottom Shape Matte Luxury Glass Candle Jars With Cork Lids\t2026-05-19~2026-06-17\t7\t0\t130\t0\t0\t0.0\t0.0\t0\t0\t0\n2.95\t1601218983077\tCustom Empty 9oz 12oz 16oz Candle Vessels Decorative Round Bottom Olive Green Amber Colorful Candle Jar With Custom Lid\t2026-05-19~2026-06-17\t7\t0\t237\t0\t3\t0.0\t42.86\t0\t0\t0\n4.09\t1601514540628\tCustom Eco Natural Beeswax Hemp Candle Wick Tabbed Organic Hemp Candle Wick Tab Coated in Beeswax for Candle Making\t2026-05-19~2026-06-17\t7\t0\t171\t2\t7\t28.57\t100.0\t2\t2\t0\n1.79\t1601525414621\tEco-Friendly Bamboo Lid Design - Non-Toxic Glass Food Storage Containers Set for Sustainable Kitchen\t2026-05-19~2026-06-17\t7\t0\t390\t1\t3\t14.29\t42.86\t1\t1\t0\n2.35\t1601583871728\t2025 New Design Red Green Gold Christmas Ornaments Set 42 PCS Hand-Painted Xmas Tree Decorations with Gift Box for Home Party\t2026-05-19~2026-06-17\t7\t0\t298\t0\t3\t0.0\t42.86\t0\t0\t0\n2.46\t1601669996137\tDIY Heat Resistant Amber Green Clear 4Oz 100Ml Candle Vessel Container Empty Glass Candle Jar With Cork Lid\t2026-05-19~2026-06-17\t7\t0\t285\t2\t4\t28.57\t57.14\t2\t1\t1\n1.42\t1601684347193\tRose Gold 30ml Fine Mist Pump Sprayer Bottle with Atomizer Pink Glass Cosmetic Toner Perfume Scent pink Perfume Bottles 15 ml\t2026-05-19~2026-06-17\t7\t0\t493\t1\t3\t14.29\t42.86\t1\t0\t1\n3.74\t1601705615326\tNew Trend Wholesale Private Label Custom Aroma Home Decoration Scented Oval Gypsum Plaster Piece\t2026-05-19~2026-06-17\t7\t0\t187\t0\t4\t14.29\t57.14\t1\t0\t1\n3.7\t1600437570544\tCustomized Square Frosted Glass Candle Jar Ceramic Candle Vessel With Lid Black for Interior Decoration\t2026-05-19~2026-06-17\t6\t0\t162\t0\t5\t0.0\t83.33\t0\t0\t0\n4.14\t1600440967757\tHuge Leopard Glass Candle Vessel Glass Jars for Candle Making Wholesale Machine Blown Clear Glass Candle Jar\t2026-05-19~2026-06-17\t6\t0\t145\t0\t4\t0.0\t66.67\t0\t0\t0\n2.15\t1600487189795\tCustom Luxury Colored Mini Empty Glass Candle Jars 65ML Desktop Nordic Home Decoration Small Glass Candle Holder\t2026-05-19~2026-06-17\t6\t0\t279\t0\t4\t0.0\t66.67\t0\t0\t0\n"
    }
  ]
}